pyfilemv/__init__.py
pyfilemv/pymv.py
pyfilemv-1.0.2.data/scripts/pymv
pyfilemv-1.0.2.dist-info/LICENSE
pyfilemv-1.0.2.dist-info/METADATA
pyfilemv-1.0.2.dist-info/WHEEL
pyfilemv-1.0.2.dist-info/top_level.txt
pyfilemv-1.0.2.dist-info/RECORD
