Metadata-Version: 2.1
Name: pyfilemv
Version: 1.0.2
Summary: Extension of the unix mv command, which will also searches through your files and updates any references to the file that you just moved.
Home-page: https://github.com/nickhir/pyfilemv/
Author: nickhir
License: UNKNOWN
Keywords: python,filesystem,move,renaming,organization
Platform: UNKNOWN
Classifier: Operating System :: Unix
Classifier: Operating System :: MacOS
Requires-Dist: colorama
Requires-Dist: tqdm
